{
  "pd_id": "pd3_social",
  "loglines": [
    {
      "logline": "65세 이상이 다섯 명 중 한 명이 된 첫 해. 한국이 고령화사회에서 초고령사회까지 25년 — 일본의 절반 시간이다. 그 25년을 한 골목·한 가족의 데이터로 압축한다.",
      "why_good": "2025년 초고령사회 공식 진입은 단순 수치가 아니라 사회 재설계 출발점이다. 한국의 진입 속도는 OECD 최고. 시청자 절반 이상이 30~50대 부양 세대로, '내 부모·내 노후'와 직접 연결된 시의성이 가장 크다. 통계청·OECD·UN 시계열이 모두 공개돼 있어 데이터 다큐 제작 가능성도 높다.",
      "ebs_fit": "노년·연령통합·세대간 부양은 EBS 공교양의 본령이며, 사교육·플랫폼이 다루지 않는 영역이다. 진단·구조 중심 톤이 정파성과 충돌하지 않는다.",
      "ai_role": "1990~2050 인구 피라미드 60년을 60초 모핑 영상으로 압축, 가상의 '1965년생 부부'를 3D로 시뮬레이션해 의료비·연금·돌봄 수요를 시청자가 시각적으로 느끼게 한다.",
      "research_summary": "통계청 2024 고령자통계 기준 2025년 65세 이상 비율 20% 돌파, 2036년 30%, 2050년 40% 전망. 한국은 고령화→초고령사회 전환 25년으로 일본(36년)·독일(40년)보다 약 1.5~2배 빠르다. 1인가구 800만 중 70세 이상 19.1%로 최다 — '혼자 늙는' 구조가 동시 진행 중.",
      "sources": [
        "https://www.kostat.go.kr/board.es?act=view&bid=10820&list_no=432917&mid=a10301010000",
        "https://mods.go.kr/board.es?mid=a10301010000&bid=10820&act=view&list_no=434103",
        "https://data.oecd.org/pop/elderly-population.htm"
      ],
      "ebs_fit_score": 9,
      "novelty_score": 7
    },
    {
      "logline": "1975년에 태어난 가구가 2025년까지 50년 동안 어떻게 살았나. 한국은 가장 가난한 나라에서 7번째 부자 나라가 됐는데, 왜 우리 집은 더 빠듯해졌는지 한 가구의 50년 가계부로 본다.",
      "why_good": "GDP 거시지표와 체감 경제 사이 괴리는 한국 사회 최대 인지부조화 중 하나다. 2030 금융부채/저축 비율 131.1%, 39세 이하 순자산 -0.3% 등 구체 데이터가 이 괴리를 설명한다. '평균의 함정' 통계 리터러시 앵글이 진영 갈등 없이 작동한다.",
      "ebs_fit": "공식 통계 기반 경제 교양은 EBS 차별점이다. 분배·세대 격차를 진영이 아닌 데이터로 설명한다는 점에서 정파성을 피할 수 있다.",
      "ai_role": "1975년부터 5년 단위로 가구 소득·주거비·교육비·자산을 AI 시뮬레이션해 한 화면에 누적시키고, 평균값과 중앙값을 동시에 그려 '평균이 거짓말하는 순간'을 시각적으로 분리한다.",
      "research_summary": "한국은행·통계청 국민계정 기준 1인당 GNI는 1975년 약 600달러에서 2025년 36,000달러대로 60배. 같은 기간 가계부채/GDP는 100% 돌파(BIS·한은). 2026 하나금융 웰스 리포트에서 39세 이하 순자산 0.3% 감소, 40~50대 큰 폭 증가로 세대 자산이전 정체가 수치로 확인됨.",
      "sources": [
        "https://kdi.re.kr/share/pressContriView?bd_no=50779",
        "https://ecos.bok.or.kr/",
        "https://kosis.kr/statHtml/statHtml.do?orgId=101&tblId=DT_1MM5006",
        "https://www.bebooja.com/calculator/korea-asset-2026"
      ],
      "ebs_fit_score": 9,
      "novelty_score": 8
    },
    {
      "logline": "229개 시군구 중 138곳이 '소멸위험'으로 분류된 해. 한국과 일본이 같은 길을 30년 시차로 걷고 있다. 두 나라 지도를 겹쳐, 사라지지 않은 마을은 무엇이 달랐나.",
      "why_good": "지방소멸은 지역 시청자와 직결된 EBS 고유 시그널이며, '소멸 고발' 단계를 넘어 '버틴 마을의 조건'으로 앵글을 옮기면 비관 일변도를 피할 수 있다. 일본 과소화(過疎化) 30년 데이터가 비교 검증축을 제공한다.",
      "ebs_fit": "지역 공동체·지방 시청자 공감은 EBS 공공성 핵심이다. 정책 비판이 아닌 구조·국제 비교 톤으로 균형 유지 가능.",
      "ai_role": "한국 229개 시군구와 일본 1,741개 시정촌의 50년 인구 변화를 동기 애니메이션 지도로 비교 시각화. 살아남은 자치구의 산업·인구 유입 변수를 머신러닝 회귀로 추출해 '버틴 변수'를 영상화한다.",
      "research_summary": "행정안전부 2026.3 기준 138개 시군구(60.2%) 소멸위험. 수도권 인구 집중 51.09%, 비수도권 자치단체 77%가 소멸 위험 자체평가. 일본 총무성 자료상 1990~2020 사이 '한계취락' 약 2만 곳 등장, 그중 일부는 이주·관광·산업 정책으로 회복. 한·일 비교는 학계에서 검증된 분석축.",
      "sources": [
        "https://www.mois.go.kr/frt/sub/a06/b06/populationDecline/screen.do",
        "https://www.soumu.go.jp/main_sosiki/jichi_gyousei/c-gyousei/2001/kaso/kasomain.html",
        "https://futurechosun.com/archives/142227"
      ],
      "ebs_fit_score": 9,
      "novelty_score": 8
    },
    {
      "logline": "AI를 한 번도 써본 적 없는 한국인이 절반이다. 그리고 그 절반은 대부분 65세 이상·저소득·장애인이다. AI 시대의 '두 개의 나라'를 데이터로 본다.",
      "why_good": "AI 격차를 청년 일자리 위협 서사가 아닌 '디지털 이용 단절층' 관점에서 본다. NIA 데이터로 단절층 규모와 분포가 정량적으로 확인되며, 사회 약자 우선이라는 EBS 가치와 정확히 일치한다. KDI의 청년 고용 영향 데이터와 함께 보면 '세대마다 다른 AI'가 보인다.",
      "ebs_fit": "디지털 약자·고령층·저소득층은 사교육·플랫폼이 다루지 않는 영역으로 EBS의 본령이다. 기술 찬반이 아닌 '함께 사는 법' 톤 유지 가능.",
      "ai_role": "전국 시군구별 AI 활용률·인터넷 이용률을 코로플레스 지도로 시각화하고, 가상의 '70대 1인가구'와 '20대 1인가구'가 같은 행정 서비스를 받을 때의 마찰을 AI 에이전트 시뮬레이션으로 비교 재현한다.",
      "research_summary": "NIA 2025 디지털정보격차 실태조사 기준 전 국민 AI 활용률 51%, 장애인·고령층·저소득층은 30% 안팎. KDI 2026 보고서 — AI 도입 확산이 남성 30~44세, 여성 15~29세 청년 고용 감소 방향으로 작용. KOCCA 2025 — 생성형 AI 콘텐츠 기업 채택률 32.1%로 산업 침투는 빠른 반면 시민 측 격차는 확대.",
      "sources": [
        "https://spri.kr/posts/view/23315?code=data_all&study_type=industry_trend",
        "https://www.kdi.re.kr/research/reportView?pub_no=18370",
        "https://www.nia.or.kr/site/nia_kor/04/_etc/digital_gap.do"
      ],
      "ebs_fit_score": 10,
      "novelty_score": 8
    },
    {
      "logline": "당신이 매일 듣는 '평균'은 거짓말을 하고 있다. 평균 연봉, 평균 자산, 평균 가구 규모 — 한국 30대의 진짜 모습은 평균·중앙값·분위수를 한 화면에 겹쳐야 보인다.",
      "why_good": "통계 리터러시는 모든 사회 의제의 기초 인프라인데 한국 교양에서 거의 비어 있는 영역이다. 정치 진영과 무관하게 작동하면서, 슈카월드식 경제 해설보다 한 단계 깊은 'EBS만이 할 수 있는 공교양' 포지션을 점유한다.",
      "ebs_fit": "공교양·미디어 리터러시는 EBS 본업이다. 어떤 세대·계층에도 정파적 메시지 없이 동일하게 유익한, 가장 안전한 톤.",
      "ai_role": "한국 30대 4,500만 데이터 포인트(통계청 가계금융복지조사)를 AI로 즉석 분포 시각화 — 평균선·중앙값선·10/50/90 분위수 선이 같은 그래프에 동시 그려지며, 시청자가 '내 위치'를 입력하면 분포 위 점으로 표시된다.",
      "research_summary": "통계청 가계금융복지조사 마이크로데이터로 분위수 분석 가능. 2030 평균 가구 자산은 약 3억 원 수준이지만 중앙값은 1억 미만, 상하위 20% 격차 8배(2026 하나금융 웰스 리포트). '평균의 함정' 개념은 OECD 통계청장 회의에서도 미디어 리터러시 핵심 주제로 다룸.",
      "sources": [
        "https://kosis.kr/statisticsList/statisticsListIndex.do?menuId=M_01_01&vwcd=MT_ZTITLE&parmTabId=M_01_01",
        "https://kdi.re.kr/share/pressContriView?bd_no=50779",
        "https://www.oecd.org/sdd/financial-stats/"
      ],
      "ebs_fit_score": 10,
      "novelty_score": 9
    },
    {
      "logline": "지난 20년간 한국이 쏟아부은 380조 원. 그런데 합계출산율은 0.72까지 내려갔다. OECD 16개국의 출산 정책과 결과를 같은 도표 위에 올린다 — 무엇이 효과 있었나, 무엇이 없었나.",
      "why_good": "저출산 정책 비판은 흔하지만 정파적으로 흐르기 쉽다. 'OECD 16개국 정책 vs 출산율 변화'를 비교축으로 두면, 진단은 객관·해석은 시청자에게 위임 가능. 정책 의도와 결과를 데이터로 분리해 보는 EBS 강점이 정확히 작동하는 영역.",
      "ebs_fit": "출산·돌봄·여성 노동은 사회 약자 영역이며 EBS 공공성에 부합. 특정 정책 옹호·비판이 아닌 '국제 비교'로 균형 톤 유지 가능.",
      "ai_role": "OECD 16개국의 출산 관련 GDP 대비 지출(현금·서비스·세제), 육아휴직 기간·소득대체율, 보육 공공성 지표와 합계출산율 변화를 한 인터랙티브 차트에 통합. 변수별 가중치를 시청자가 조정하면 '내가 생각한 정책 조합'이 어떤 OECD 국가에 가까운지 AI가 매칭해 알려준다.",
      "research_summary": "통계청 2025 인구동향 — 2024년 합계출산율 0.72, 2025년 잠정 0.74로 소폭 반등. 보건복지부·기재부 추산 2006~2025 저출산 예산 약 380조 원. OECD Family Database — 프랑스 1.79, 스웨덴 1.66, 독일 1.46, 일본 1.20, 한국 0.72. GDP 대비 가족 지출 OECD 평균 2.1%, 한국 1.6%(2022 기준).",
      "sources": [
        "https://kostat.go.kr/portal/korea/kor_nw/1/2/2/index.board",
        "https://www.oecd.org/els/family/database.htm",
        "https://www.korea.kr/news/policyNewsView.do"
      ],
      "ebs_fit_score": 9,
      "novelty_score": 7
    }
  ]
}
